markdone/__init__.py
markdone/__main__.py
markdone-0.0.0.dist-info/licenses/LICENSE
markdone-0.0.0.dist-info/METADATA
markdone-0.0.0.dist-info/WHEEL
markdone-0.0.0.dist-info/entry_points.txt
markdone-0.0.0.dist-info/top_level.txt
markdone-0.0.0.dist-info/RECORD
